FullAdder/full_adder.v
module full_adder (

    input A, B, C,
    output sum, carry
);

wire half_sum, halfcarry_1, halfcarry_2;

half_adder HA1 (A, B, half_sum, halfcarry_1);
half_adder HA2 (half_sum, C, sum, halfcarry_2);

assign carry = halfcarry_1 | halfcarry_2;

endmodule

module half_adder (

    input A, B,
    output S, C
);

assign S = A ^ B;
assign C = A & B;

endmodule

FullAdder/full_adder_tb.v
`timescale 1ns/1ns
`include "full_adder.v"

module full_adder_tb;

reg A, B, C;
wire sum, carry;

full_adder uut (A, B, C, sum, carry);

initial begin 
    $dumpfile ("full_adder_tb.vcd");
    $dumpvars(0, full_adder_tb);

    A = 0;
    B = 0;
    C = 0;
    #20

    A = 0;
    B = 0;
    C = 1;
    #20

    A = 0;
    B = 1;
    C = 0;
    #20

    A = 0;
    B = 1;
    C = 1;
    #20

    A = 1;
    B = 0;
    C = 0;
    #20

    A = 1;
    B = 0;
    C = 1;
    #20

    A = 1;
    B = 1;
    C = 0;
    #20

    A = 1;
    B = 1;
    C = 1;
    #20


   

    $display ("Task Completed !!");

end
endmodule

FullAdder/full_adder_tb.vcd
$date
	Mon Jul 25 13:32:55 2022
$end
$version
	Icarus Verilog
$end
$timescale
	1ns
$end
$scope module full_adder_tb $end
$var wire 1 ! sum $end
$var wire 1 " carry $end
$var reg 1 # A $end
$var reg 1 $ B $end
$var reg 1 % C $end
$scope module uut $end
$var wire 1 # A $end
$var wire 1 $ B $end
$var wire 1 % C $end
$var wire 1 " carry $end
$var wire 1 ! sum $end
$var wire 1 & halfcarry_2 $end
$var wire 1 ' halfcarry_1 $end
$var wire 1 ( half_sum $end
$scope module HA1 $end
$var wire 1 # A $end
$var wire 1 $ B $end
$var wire 1 ' C $end
$var wire 1 ( S $end
$upscope $end
$scope module HA2 $end
$var wire 1 ( A $end
$var wire 1 % B $end
$var wire 1 & C $end
$var wire 1 ! S $end
$upscope $end
$upscope $end
$upscope $end
$enddefinitions $end
$comment Show the parameter values. $end
$dumpall
$end
#0
$dumpvars
0(
0'
0&
0%
0$
0#
0"
0!
$end
#20
1!
1%
#40
1(
0%
1$
#60
1"
0!
1&
1%
#80
0"
1!
0&
0%
0$
1#
#100
1"
0!
1&
1%
#120
0&
0(
1'
0%
1$
#140
1!
1%
